setup.py
jmc_beet.egg-info/PKG-INFO
jmc_beet.egg-info/SOURCES.txt
jmc_beet.egg-info/dependency_links.txt
jmc_beet.egg-info/entry_points.txt
jmc_beet.egg-info/requires.txt
jmc_beet.egg-info/top_level.txt
jmcbeet/__init__.py
jmcbeet/__main__.py
jmcbeet/config.py