Metadata-Version: 2.1
Name: jmc-beet
Version: 0.0.1a8
Summary: A Beet plugin that act as an adapter for JMC
Author: WingedSeal
Author-email: firm09719@gmail.com
License: MIT License
Project-URL: Documentation, https://jmc.wingedseal.com/
Project-URL: Repository, https://github.com/WingedSeal/jmc-beet
Keywords: python,minecraft,mcfunction,datapack,compiler,beet
Classifier: Development Status :: 5 - Production/Stable
Classifier: Intended Audience :: Developers
Classifier: Programming Language :: Python :: 3.10
Classifier: Programming Language :: Python :: 3.11
Classifier: Programming Language :: Python :: 3.12
Classifier: Operating System :: Unix
Classifier: Operating System :: MacOS :: MacOS X
Classifier: Operating System :: Microsoft :: Windows
Requires-Python: >=3.10
